miniauth/__init__.py
miniauth/auth.py
miniauth/main.py
miniauth/storage.py
miniauth/typing.py
miniauth/utils.py
miniauth-0.2.0.dist-info/DESCRIPTION.rst
miniauth-0.2.0.dist-info/METADATA
miniauth-0.2.0.dist-info/RECORD
miniauth-0.2.0.dist-info/WHEEL
miniauth-0.2.0.dist-info/entry_points.txt
miniauth-0.2.0.dist-info/metadata.json
miniauth-0.2.0.dist-info/top_level.txt
miniauth-0.2.0.dist-info/zip-safe
