Metadata-Version: 2.0
Name: miniauth
Version: 0.2.0
Summary: Simple local user authentication
Home-page: https://github.com/farzadghanei/miniauth
Author: Farzad Ghanei
Author-email: farzad.ghanei@gmail.com
License: MIT
Keywords: auth userdb
Platform: UNKNOWN
Classifier: Development Status :: 3 - Alpha
Classifier: Intended Audience :: Developers
Classifier: Intended Audience :: System Administrators
Classifier: License :: OSI Approved :: MIT License
Classifier: Operating System :: OS Independent
Classifier: Programming Language :: Python
Classifier: Programming Language :: Python :: 2
Classifier: Programming Language :: Python :: 2.7
Classifier: Programming Language :: Python :: 3
Classifier: Programming Language :: Python :: 3.4
Classifier: Programming Language :: Python :: 3.5
Classifier: Programming Language :: Python :: 3.6
Classifier: Programming Language :: Python :: 3.7
Classifier: Programming Language :: Python :: Implementation :: CPython
Classifier: Programming Language :: Python :: Implementation :: PyPy
Classifier: Topic :: Software Development :: Libraries
Classifier: Topic :: Software Development :: Libraries :: Python Modules
Classifier: Topic :: Utilities
Provides-Extra: dev
Provides-Extra: dev
Requires-Dist: pytest; extra == 'dev'
Requires-Dist: mock; extra == 'dev'
Requires-Dist: typing; extra == 'dev'
Requires-Dist: pycodestyle; extra == 'dev'
